coinsignal-1.6.5.dist-info/METADATA
coinsignal-1.6.5.dist-info/RECORD
coinsignal-1.6.5.dist-info/WHEEL
coinsignal-1.6.5.dist-info/top_level.txt
coinsignal/__init__.py
coinsignal/_ext.pyd
coinsignal/data.py
coinsignal/feature.py
coinsignal/label.py
coinsignal/model.py
coinsignal/parallel.py
coinsignal/sampler.py
coinsignal/tools.py
coinsignal-1.6.5.dist-info/RECORD
