Metadata-Version: 2.4
Name: coinsignal
Version: 1.6.5
Summary: coin data analysis and return predicting framework
Author: Zehao Yang
Requires-Python: >=3.8
Requires-Dist: numpy>=1.20.0
Requires-Dist: pandas>=1.3.0
Requires-Dist: lightgbm>=3.3.0
Requires-Dist: scikit-learn>=1.0.0
Requires-Dist: matplotlib>=3.3.0
Requires-Dist: pyyaml>=5.4.0
Requires-Dist: joblib>=1.0.0
Requires-Dist: cython>=0.29.0
Dynamic: author
Dynamic: description
Dynamic: description-content-type
Dynamic: requires-dist
Dynamic: requires-python
Dynamic: summary
